async_client_decorator/__init__.py
async_client_decorator-1.0.0.dist-info/LICENSE
async_client_decorator-1.0.0.dist-info/METADATA
async_client_decorator-1.0.0.dist-info/WHEEL
async_client_decorator-1.0.0.dist-info/top_level.txt
async_client_decorator-1.0.0.dist-info/RECORD
