Metadata-Version: 2.1
Name: async_client_decorator
Version: 1.0.0
Summary: async_client_decorator is now ahttp-client.
Home-page: https://github.com/gunyu1019/ahttp-client
Author: gunyu1019
Author-email: gunyu1019@yhs.kr
License: MIT
Classifier: Development Status :: 7 - Inactive
Classifier: License :: OSI Approved :: MIT License
Classifier: Intended Audience :: Developers
Requires-Python: >=3.10
License-File: LICENSE
Requires-Dist: ahttp-client
